leveldb.cpython-312-darwin.so
leveldb_312-1.0.0.dist-info/licenses/LICENSE
leveldb_312-1.0.0.dist-info/METADATA
leveldb_312-1.0.0.dist-info/WHEEL
leveldb_312-1.0.0.dist-info/top_level.txt
leveldb_312-1.0.0.dist-info/RECORD
